{"statuses":[{"created_at":"Tue Jul 18 01:29:40 +0000 2017","id":887122163118911500,"id_str":"887122163118911488","text":"エミルさん、７月が誕生日でしたね…エクストリーム型抜きのとき輝いてましたね… https://t.co/xEMvquiaG8","truncated":false,"entities":{"hashtags":[],"symbols":[],"user_mentions":[],"urls":[],"media":[{"id":887121734968590300,"id_str":"887121734968590336","indices":[39,62],"media_url":"http://pbs.twimg.com/media/DE-whI1UwAAhjcO.jpg","media_url_https":"https://pbs.twimg.com/media/DE-whI1UwAAhjcO.jpg","url":"https://t.co/xEMvquiaG8","display_url":"pic.twitter.com/xEMvquiaG8","expanded_url":"https://twitter.com/kubo_3260_yuri/status/887122163118911488/photo/1","type":"photo","sizes":{"thumb":{"w":150,"h":150,"resize":"crop"},"large":{"w":709,"h":1006,"resize":"fit"},"small":{"w":479,"h":680,"resize":"fit"},"medium":{"w":709,"h":1006,"resize":"fit"}}}]},"extended_entities":{"media":[{"id":887121734968590300,"id_str":"887121734968590336","indices":[39,62],"media_url":"http://pbs.twimg.com/media/DE-whI1UwAAhjcO.jpg","media_url_https":"https://pbs.twimg.com/media/DE-whI1UwAAhjcO.jpg","url":"https://t.co/xEMvquiaG8","display_url":"pic.twitter.com/xEMvquiaG8","expanded_url":"https://twitter.com/kubo_3260_yuri/status/887122163118911488/photo/1","type":"photo","sizes":{"thumb":{"w":150,"h":150,"resize":"crop"},"large":{"w":709,"h":1006,"resize":"fit"},"small":{"w":479,"h":680,"resize":"fit"},"medium":{"w":709,"h":1006,"resize":"fit"}}}]},"metadata":{"iso_language_code":"ja","result_type":"recent"},"source":"<a href=\"http://twitter.com\" rel=\"nofollow\">Twitter Web Client</a>","in_reply_to_status_id":null,"in_reply_to_status_id_str":null,"in_reply_to_user_id":null,"in_reply_to_user_id_str":null,"in_reply_to_screen_name":null,"user":{"id":843208358186295300,"id_str":"843208358186295296","name":"KUBO!!!","screen_name":"kubo_3260_yuri","location":"Japan","description":"Mitsurou KUBO (main account→@kubo_3260 )/This account is only tweet about #yurionice/ [YURI!!! on ICE] official info→@yurionice_PR","url":"https://t.co/pCRm3EshOz","entities":{"url":{"urls":[{"url":"https://t.co/pCRm3EshOz","expanded_url":"http://yurionice.com","display_url":"yurionice.com","indices":[0,23]}]},"description":{"urls":[]}},"protected":false,"followers_count":77837,"friends_count":8,"listed_count":566,"created_at":"Sat Mar 18 21:11:53 +0000 2017","favourites_count":73,"utc_offset":null,"time_zone":null,"geo_enabled":false,"verified":false,"statuses_count":374,"lang":"ja","contributors_enabled":false,"is_translator":false,"is_translation_enabled":false,"profile_background_color":"F5F8FA","profile_background_image_url":null,"profile_background_image_url_https":null,"profile_background_tile":false,"profile_image_url":"http://pbs.twimg.com/profile_images/843221168744091648/0iKF9b4y_normal.jpg","profile_image_url_https":"https://pbs.twimg.com/profile_images/843221168744091648/0iKF9b4y_normal.jpg","profile_banner_url":"https://pbs.twimg.com/profile_banners/843208358186295296/1489874568","profile_link_color":"1DA1F2","profile_sidebar_border_color":"C0DEED","profile_sidebar_fill_color":"DDEEF6","profile_text_color":"333333","profile_use_background_image":true,"has_extended_profile":false,"default_profile":true,"default_profile_image":false,"following":false,"follow_request_sent":false,"notifications":false,"translator_type":"none"},"geo":null,"coordinates":null,"place":null,"contributors":null,"is_quote_status":false,"retweet_count":1069,"favorite_count":2804,"favorited":false,"retweeted":false,"possibly_sensitive":false,"lang":"ja"},{"created_at":"Tue Jul 18 01:27:39 +0000 2017","id":887121655931093000,"id_str":"887121655931092992","text":"スンギルさん、６月が誕生日でしたよね…お元気でしょうか… https://t.co/wy31ijntMY","truncated":false,"entities":{"hashtags":[],"symbols":[],"user_mentions":[],"urls":[],"media":[{"id":887120806756499500,"id_str":"887120806756499456","indices":[29,52],"media_url":"http://pbs.twimg.com/media/DE-vrG-UQAAreHW.jpg","media_url_https":"https://pbs.twimg.com/media/DE-vrG-UQAAreHW.jpg","url":"https://t.co/wy31ijntMY","display_url":"pic.twitter.com/wy31ijntMY","expanded_url":"https://twitter.com/kubo_3260_yuri/status/887121655931092992/photo/1","type":"photo","sizes":{"medium":{"w":709,"h":1006,"resize":"fit"},"thumb":{"w":150,"h":150,"resize":"crop"},"small":{"w":479,"h":680,"resize":"fit"},"large":{"w":709,"h":1006,"resize":"fit"}}}]},"extended_entities":{"media":[{"id":887120806756499500,"id_str":"887120806756499456","indices":[29,52],"media_url":"http://pbs.twimg.com/media/DE-vrG-UQAAreHW.jpg","media_url_https":"https://pbs.twimg.com/media/DE-vrG-UQAAreHW.jpg","url":"https://t.co/wy31ijntMY","display_url":"pic.twitter.com/wy31ijntMY","expanded_url":"https://twitter.com/kubo_3260_yuri/status/887121655931092992/photo/1","type":"photo","sizes":{"medium":{"w":709,"h":1006,"resize":"fit"},"thumb":{"w":150,"h":150,"resize":"crop"},"small":{"w":479,"h":680,"resize":"fit"},"large":{"w":709,"h":1006,"resize":"fit"}}}]},"metadata":{"iso_language_code":"ja","result_type":"recent"},"source":"<a href=\"http://twitter.com\" rel=\"nofollow\">Twitter Web Client</a>","in_reply_to_status_id":null,"in_reply_to_status_id_str":null,"in_reply_to_user_id":null,"in_reply_to_user_id_str":null,"in_reply_to_screen_name":null,"user":{"id":843208358186295300,"id_str":"843208358186295296","name":"KUBO!!!","screen_name":"kubo_3260_yuri","location":"Japan","description":"Mitsurou KUBO (main account→@kubo_3260 )/This account is only tweet about #yurionice/ [YURI!!! on ICE] official info→@yurionice_PR","url":"https://t.co/pCRm3EshOz","entities":{"url":{"urls":[{"url":"https://t.co/pCRm3EshOz","expanded_url":"http://yurionice.com","display_url":"yurionice.com","indices":[0,23]}]},"description":{"urls":[]}},"protected":false,"followers_count":77837,"friends_count":8,"listed_count":566,"created_at":"Sat Mar 18 21:11:53 +0000 2017","favourites_count":73,"utc_offset":null,"time_zone":null,"geo_enabled":false,"verified":false,"statuses_count":374,"lang":"ja","contributors_enabled":false,"is_translator":false,"is_translation_enabled":false,"profile_background_color":"F5F8FA","profile_background_image_url":null,"profile_background_image_url_https":null,"profile_background_tile":false,"profile_image_url":"http://pbs.twimg.com/profile_images/843221168744091648/0iKF9b4y_normal.jpg","profile_image_url_https":"https://pbs.twimg.com/profile_images/843221168744091648/0iKF9b4y_normal.jpg","profile_banner_url":"https://pbs.twimg.com/profile_banners/843208358186295296/1489874568","profile_link_color":"1DA1F2","profile_sidebar_border_color":"C0DEED","profile_sidebar_fill_color":"DDEEF6","profile_text_color":"333333","profile_use_background_image":true,"has_extended_profile":false,"default_profile":true,"default_profile_image":false,"following":false,"follow_request_sent":false,"notifications":false,"translator_type":"none"},"geo":null,"coordinates":null,"place":null,"contributors":null,"is_quote_status":false,"retweet_count":1193,"favorite_count":3074,"favorited":false,"retweeted":false,"possibly_sensitive":false,"lang":"ja"},{"created_at":"Tue Jul 18 01:15:04 +0000 2017","id":887118489068097500,"id_str":"887118489068097536","text":"＼もう応募しましたか？／\n平日毎日当たる！\n #アサヒドライゼロプレゼント ！\n締切は７／１９　午前９時５９分まで！\n① @asahibeer_jp をフォロー\n②この投稿をリツイート⇒… https://t.co/chv1RPHzd5","truncated":true,"entities":{"hashtags":[{"text":"アサヒドライゼロプレゼント","indices":[23,37]}],"symbols":[],"user_mentions":[{"screen_name":"asahibeer_jp","name":"アサヒビール ASAHIBEER","id":561669474,"id_str":"561669474","indices":[61,74]}],"urls":[{"url":"https://t.co/chv1RPHzd5","expanded_url":"https://twitter.com/i/web/status/887118489068097536","display_url":"twitter.com/i/web/status/8…","indices":[95,118]}]},"metadata":{"iso_language_code":"ja","result_type":"recent"},"source":"<a href=\"http://engagemanager.tribalmedia.co.jp/\" rel=\"nofollow\">EngageManager</a>","in_reply_to_status_id":null,"in_reply_to_status_id_str":null,"in_reply_to_user_id":null,"in_reply_to_user_id_str":null,"in_reply_to_screen_name":null,"user":{"id":561669474,"id_str":"561669474","name":"アサヒビール ASAHIBEER","screen_name":"asahibeer_jp","location":"","description":"アサヒビール公式です！飲酒は20歳になってから。飲酒運転は法律で禁止されています。フォローは20歳以上の方限定です。 【ご利用規約】https://t.co/87vTVzXt5G【お問い合わせ】https://t.co/2cgJAsil8T","url":"http://t.co/JKM5mqm9OI","entities":{"url":{"urls":[{"url":"http://t.co/JKM5mqm9OI","expanded_url":"http://www.asahibeer.co.jp/","display_url":"asahibeer.co.jp","indices":[0,22]}]},"description":{"urls":[{"url":"https://t.co/87vTVzXt5G","expanded_url":"https://goo.gl/LxiI3c","display_url":"goo.gl/LxiI3c","indices":[66,89]},{"url":"https://t.co/2cgJAsil8T","expanded_url":"https://goo.gl/aOceCQ","display_url":"goo.gl/aOceCQ","indices":[97,120]}]}},"protected":false,"followers_count":614833,"friends_count":30,"listed_count":1431,"created_at":"Tue Apr 24 00:28:13 +0000 2012","favourites_count":1,"utc_offset":32400,"time_zone":"Tokyo","geo_enabled":false,"verified":true,"statuses_count":631329,"lang":"ja","contributors_enabled":false,"is_translator":false,"is_translation_enabled":false,"profile_background_color":"FFFFFF","profile_background_image_url":"http://pbs.twimg.com/profile_background_images/378800000182351567/6y9isvcT.jpeg","profile_background_image_url_https":"https://pbs.twimg.com/profile_background_images/378800000182351567/6y9isvcT.jpeg","profile_background_tile":false,"profile_image_url":"http://pbs.twimg.com/profile_images/551878698152914944/JwmVmkeK_normal.png","profile_image_url_https":"https://pbs.twimg.com/profile_images/551878698152914944/JwmVmkeK_normal.png","profile_banner_url":"https://pbs.twimg.com/profile_banners/561669474/1496216924","profile_link_color":"0084B4","profile_sidebar_border_color":"FFFFFF","profile_sidebar_fill_color":"DDEEF6","profile_text_color":"333333","profile_use_background_image":true,"has_extended_profile":false,"default_profile":false,"default_profile_image":false,"following":false,"follow_request_sent":false,"notifications":false,"translator_type":"none"},"geo":null,"coordinates":null,"place":null,"contributors":null,"is_quote_status":false,"retweet_count":2198,"favorite_count":207,"favorited":false,"retweeted":false,"possibly_sensitive":false,"lang":"ja"},{"created_at":"Tue Jul 18 01:12:34 +0000 2017","id":887117859796549600,"id_str":"887117859796549636","text":"ディズニー実写版「アラジン」の主要キャストが正式発表。主人公アラジン役にはエジプトとカナダのハーフである新人メナ・マスード。ジャスミン役には「パワーレンジャー」のナオミ・スコット。魔神ジーニーの声をウィル・スミスが演じる。「シャー… https://t.co/S3emeM82Up","truncated":true,"entities":{"hashtags":[],"symbols":[],"user_mentions":[],"urls":[{"url":"https://t.co/S3emeM82Up","expanded_url":"https://twitter.com/i/web/status/887117859796549636","display_url":"twitter.com/i/web/status/8…","indices":[117,140]}]},"metadata":{"iso_language_code":"ja","result_type":"recent"},"source":"<a href=\"http://twitter.com\" rel=\"nofollow\">Twitter Web Client</a>","in_reply_to_status_id":null,"in_reply_to_status_id_str":null,"in_reply_to_user_id":null,"in_reply_to_user_id_str":null,"in_reply_to_screen_name":null,"user":{"id":95379163,"id_str":"95379163","name":"映画情報 オスカーノユクエ","screen_name":"oscarnoyukue","location":"","description":"総合映画情報を発信するサイト「オスカーノユクエ」管理人のTwitter。映画情報ツイートの主なソースは、Deadline, IMDb, The Playlist, Variety, Hollywood Reporter, JoBloなど。","url":"https://t.co/9cyGcIOZV6","entities":{"url":{"urls":[{"url":"https://t.co/9cyGcIOZV6","expanded_url":"http://oscar-no-yukue.com","display_url":"oscar-no-yukue.com","indices":[0,23]}]},"description":{"urls":[]}},"protected":false,"followers_count":104913,"friends_count":78,"listed_count":2547,"created_at":"Tue Dec 08 08:16:38 +0000 2009","favourites_count":3,"utc_offset":32400,"time_zone":"Tokyo","geo_enabled":false,"verified":false,"statuses_count":15351,"lang":"ja","contributors_enabled":false,"is_translator":false,"is_translation_enabled":false,"profile_background_color":"C0DEED","profile_background_image_url":"http://abs.twimg.com/images/themes/theme1/bg.png","profile_background_image_url_https":"https://abs.twimg.com/images/themes/theme1/bg.png","profile_background_tile":false,"profile_image_url":"http://pbs.twimg.com/profile_images/564516374/twitter_icon_normal.jpg","profile_image_url_https":"https://pbs.twimg.com/profile_images/564516374/twitter_icon_normal.jpg","profile_banner_url":"https://pbs.twimg.com/profile_banners/95379163/1424318969","profile_link_color":"1DA1F2","profile_sidebar_border_color":"C0DEED","profile_sidebar_fill_color":"DDEEF6","profile_text_color":"333333","profile_use_background_image":true,"has_extended_profile":false,"default_profile":true,"default_profile_image":false,"following":false,"follow_request_sent":false,"notifications":false,"translator_type":"none"},"geo":null,"coordinates":null,"place":null,"contributors":null,"is_quote_status":false,"retweet_count":620,"favorite_count":553,"favorited":false,"retweeted":false,"possibly_sensitive":false,"lang":"ja"},{"created_at":"Tue Jul 18 01:11:05 +0000 2017","id":887117489410261000,"id_str":"887117489410260992","text":"大千穐楽から一夜明け、興奮冷めやらぬ中、ライブビューイング特別編集版にて舞台「黒子のバスケ」OVER-DRIVE の期間限定配信が決定しました！8/1日（火）よりぜひご視聴ください!!　https://t.co/jlD10yM9pb　#くろステ","truncated":false,"entities":{"hashtags":[{"text":"くろステ","indices":[117,122]}],"symbols":[],"user_mentions":[],"urls":[{"url":"https://t.co/jlD10yM9pb","expanded_url":"http://www.kurobas-stage.com/topics.html","display_url":"kurobas-stage.com/topics.html","indices":[93,116]}]},"metadata":{"iso_language_code":"ja","result_type":"recent"},"source":"<a href=\"http://twitter.com\" rel=\"nofollow\">Twitter Web Client</a>","in_reply_to_status_id":null,"in_reply_to_status_id_str":null,"in_reply_to_user_id":null,"in_reply_to_user_id_str":null,"in_reply_to_screen_name":null,"user":{"id":4612140312,"id_str":"4612140312","name":"舞台「黒子のバスケ」","screen_name":"kurobasstage","location":"","description":"舞台「黒子のバスケ」公式アカウント。中屋敷法仁演出、小野賢章、安里勇哉、黒羽麻璃央、畠山遼、小沼将太、太田基裕ほか出演で待望の第二弾上演決定！【東京】2017年6月22日(木)～7月9日(日)AiiA 2.5 Theater Tokyo【大阪】2017年7月13日(木)～7月17日(月・祝)森ノ宮ピロティホール","url":"https://t.co/Abx3gSBQgf","entities":{"url":{"urls":[{"url":"https://t.co/Abx3gSBQgf","expanded_url":"http://www.kurobas-stage.com/","display_url":"kurobas-stage.com","indices":[0,23]}]},"description":{"urls":[]}},"protected":false,"followers_count":31046,"friends_count":0,"listed_count":801,"created_at":"Sun Dec 20 12:12:51 +0000 2015","favourites_count":0,"utc_offset":-25200,"time_zone":"Pacific Time (US & Canada)","geo_enabled":false,"verified":false,"statuses_count":468,"lang":"ja","contributors_enabled":false,"is_translator":false,"is_translation_enabled":false,"profile_background_color":"000000","profile_background_image_url":"http://abs.twimg.com/images/themes/theme1/bg.png","profile_background_image_url_https":"https://abs.twimg.com/images/themes/theme1/bg.png","profile_background_tile":false,"profile_image_url":"http://pbs.twimg.com/profile_images/678554577369612288/AMEtg_cC_normal.jpg","profile_image_url_https":"https://pbs.twimg.com/profile_images/678554577369612288/AMEtg_cC_normal.jpg","profile_banner_url":"https://pbs.twimg.com/profile_banners/4612140312/1497429914","profile_link_color":"DD2E44","profile_sidebar_border_color":"000000","profile_sidebar_fill_color":"000000","profile_text_color":"000000","profile_use_background_image":false,"has_extended_profile":true,"default_profile":false,"default_profile_image":false,"following":false,"follow_request_sent":false,"notifications":false,"translator_type":"none"},"geo":null,"coordinates":null,"place":null,"contributors":null,"is_quote_status":false,"retweet_count":770,"favorite_count":772,"favorited":false,"retweeted":false,"possibly_sensitive":false,"lang":"ja"},{"created_at":"Tue Jul 18 01:07:51 +0000 2017","id":887116672745693200,"id_str":"887116672745693184","text":"追悼ジョージ・A・ロメロ監督。4コマ漫画ネコノヒー「ゾンビ」/Zombie  https://t.co/Dq7XqVCxDq https://t.co/uP9R6cqESc","truncated":false,"entities":{"hashtags":[],"symbols":[],"user_mentions":[],"urls":[{"url":"https://t.co/Dq7XqVCxDq","expanded_url":"http://www.q-rais.com/entry/2017/07/18/100637","display_url":"q-rais.com/entry/2017/07/…","indices":[39,62]}],"media":[{"id":887116640147484700,"id_str":"887116640147484672","indices":[63,86],"media_url":"http://pbs.twimg.com/media/DE-r4lJUMAAQ8hl.jpg","media_url_https":"https://pbs.twimg.com/media/DE-r4lJUMAAQ8hl.jpg","url":"https://t.co/uP9R6cqESc","display_url":"pic.twitter.com/uP9R6cqESc","expanded_url":"https://twitter.com/Qrais_Usagi/status/887116672745693184/photo/1","type":"photo","sizes":{"large":{"w":744,"h":2048,"resize":"fit"},"thumb":{"w":150,"h":150,"resize":"crop"},"medium":{"w":436,"h":1200,"resize":"fit"},"small":{"w":247,"h":680,"resize":"fit"}}}]},"extended_entities":{"media":[{"id":887116640147484700,"id_str":"887116640147484672","indices":[63,86],"media_url":"http://pbs.twimg.com/media/DE-r4lJUMAAQ8hl.jpg","media_url_https":"https://pbs.twimg.com/media/DE-r4lJUMAAQ8hl.jpg","url":"https://t.co/uP9R6cqESc","display_url":"pic.twitter.com/uP9R6cqESc","expanded_url":"https://twitter.com/Qrais_Usagi/status/887116672745693184/photo/1","type":"photo","sizes":{"large":{"w":744,"h":2048,"resize":"fit"},"thumb":{"w":150,"h":150,"resize":"crop"},"medium":{"w":436,"h":1200,"resize":"fit"},"small":{"w":247,"h":680,"resize":"fit"}}}]},"metadata":{"iso_language_code":"ja","result_type":"recent"},"source":"<a href=\"http://twitter.com\" rel=\"nofollow\">Twitter Web Client</a>","in_reply_to_status_id":null,"in_reply_to_status_id_str":null,"in_reply_to_user_id":null,"in_reply_to_user_id_str":null,"in_reply_to_screen_name":null,"user":{"id":858604256751788000,"id_str":"858604256751788032","name":"キューライス","screen_name":"Qrais_Usagi","location":"日本","description":"漫画家。   オモコロ→https://t.co/Mu96990UN6  XOYリーグ→https://t.co/dHiIVNA0oC  短編アニメhttps://t.co/HlBQAFfRM1ご依頼はこちらへqraisqrais@gmail.com","url":"https://t.co/FTRKplUt5d","entities":{"url":{"urls":[{"url":"https://t.co/FTRKplUt5d","expanded_url":"http://www.q-rais.com","display_url":"q-rais.com","indices":[0,23]}]},"description":{"urls":[{"url":"https://t.co/Mu96990UN6","expanded_url":"http://omocoro.jp/writer","display_url":"omocoro.jp/writer","indices":[12,35]},{"url":"https://t.co/dHiIVNA0oC","expanded_url":"http://xoy.webtoons.com/ja/challenge","display_url":"xoy.webtoons.com/ja/challenge","indices":[44,67]},{"url":"https://t.co/HlBQAFfRM1","expanded_url":"https://www.youtube.com/watch?v=48-RA4BNXVc","display_url":"youtube.com/watch?v=48-RA4…","indices":[74,97]}]}},"protected":false,"followers_count":118534,"friends_count":92,"listed_count":548,"created_at":"Sun Apr 30 08:49:41 +0000 2017","favourites_count":1028,"utc_offset":null,"time_zone":null,"geo_enabled":false,"verified":false,"statuses_count":218,"lang":"ja","contributors_enabled":false,"is_translator":false,"is_translation_enabled":false,"profile_background_color":"F5F8FA","profile_background_image_url":null,"profile_background_image_url_https":null,"profile_background_tile":false,"profile_image_url":"http://pbs.twimg.com/profile_images/858606013938716672/92qPwUv5_normal.jpg","profile_image_url_https":"https://pbs.twimg.com/profile_images/858606013938716672/92qPwUv5_normal.jpg","profile_banner_url":"https://pbs.twimg.com/profile_banners/858604256751788032/1493542909","profile_link_color":"1DA1F2","profile_sidebar_border_color":"C0DEED","profile_sidebar_fill_color":"DDEEF6","profile_text_color":"333333","profile_use_background_image":true,"has_extended_profile":true,"default_profile":true,"default_profile_image":false,"following":false,"follow_request_sent":false,"notifications":false,"translator_type":"none"},"geo":null,"coordinates":null,"place":null,"contributors":null,"is_quote_status":false,"retweet_count":818,"favorite_count":2073,"favorited":false,"retweeted":false,"possibly_sensitive":false,"lang":"ja"},{"created_at":"Tue Jul 18 01:03:10 +0000 2017","id":887115493697388500,"id_str":"887115493697388545","text":"【J-WORLD】「J-WORLD Collection」の第4弾は、火神大我！！描き下ろしイラストのグッズや景品、フードメニューや等身大パネル展示も！期間は8月1日(火)～8月23日(水)まで… https://t.co/E64ZEVykX2","truncated":true,"entities":{"hashtags":[],"symbols":[],"user_mentions":[],"urls":[{"url":"https://t.co/E64ZEVykX2","expanded_url":"https://twitter.com/i/web/status/887115493697388545","display_url":"twitter.com/i/web/status/8…","indices":[99,122]}]},"metadata":{"iso_language_code":"ja","result_type":"recent"},"source":"<a href=\"http://twitter.com\" rel=\"nofollow\">Twitter Web Client</a>","in_reply_to_status_id":null,"in_reply_to_status_id_str":null,"in_reply_to_user_id":null,"in_reply_to_user_id_str":null,"in_reply_to_screen_name":null,"user":{"id":401831759,"id_str":"401831759","name":"アニメ黒子のバスケ","screen_name":"kurobasanime","location":"誠凛高校バスケ部","description":"アニメ「黒子のバスケ」の公式Twitterです。アニメに関するいろんな情報を関係者がつぶやきます。ハッシュタグ【#kurobas】　※フォロー返し、コメントリプライは実施していません。ご容赦ください。","url":"http://t.co/6U9iBqTBu9","entities":{"url":{"urls":[{"url":"http://t.co/6U9iBqTBu9","expanded_url":"http://www.kurobas.com/","display_url":"kurobas.com","indices":[0,22]}]},"description":{"urls":[]}},"protected":false,"followers_count":284009,"friends_count":0,"listed_count":4762,"created_at":"Mon Oct 31 04:44:26 +0000 2011","favourites_count":0,"utc_offset":32400,"time_zone":"Tokyo","geo_enabled":false,"verified":false,"statuses_count":3737,"lang":"ja","contributors_enabled":false,"is_translator":false,"is_translation_enabled":true,"profile_background_color":"C0DEED","profile_background_image_url":"http://abs.twimg.com/images/themes/theme1/bg.png","profile_background_image_url_https":"https://abs.twimg.com/images/themes/theme1/bg.png","profile_background_tile":false,"profile_image_url":"http://pbs.twimg.com/profile_images/681302376263761920/9CPjjeYo_normal.png","profile_image_url_https":"https://pbs.twimg.com/profile_images/681302376263761920/9CPjjeYo_normal.png","profile_banner_url":"https://pbs.twimg.com/profile_banners/401831759/1496211614","profile_link_color":"1DA1F2","profile_sidebar_border_color":"C0DEED","profile_sidebar_fill_color":"DDEEF6","profile_text_color":"333333","profile_use_background_image":true,"has_extended_profile":false,"default_profile":true,"default_profile_image":false,"following":false,"follow_request_sent":false,"notifications":false,"translator_type":"none"},"geo":null,"coordinates":null,"place":null,"contributors":null,"is_quote_status":false,"retweet_count":1488,"favorite_count":1489,"favorited":false,"retweeted":false,"possibly_sensitive":false,"lang":"ja"},{"created_at":"Tue Jul 18 01:03:00 +0000 2017","id":887115453948088300,"id_str":"887115453948088320","text":"〜情報解禁〜\n『ミュージカル「黒執事」-Tango on the Campania -』\nエドワード・ミッドフォード役で出演致します！\n\n素敵な舞台を届けられるように、現状に甘んじる事なく、常に向上心を持って頑張りたいと思います！… https://t.co/2yPEmtwCLE","truncated":true,"entities":{"hashtags":[],"symbols":[],"user_mentions":[],"urls":[{"url":"https://t.co/2yPEmtwCLE","expanded_url":"https://twitter.com/i/web/status/887115453948088320","display_url":"twitter.com/i/web/status/8…","indices":[117,140]}]},"metadata":{"iso_language_code":"ja","result_type":"recent"},"source":"<a href=\"http://twitter.com/download/iphone\" rel=\"nofollow\">Twitter for iPhone</a>","in_reply_to_status_id":null,"in_reply_to_status_id_str":null,"in_reply_to_user_id":null,"in_reply_to_user_id_str":null,"in_reply_to_screen_name":null,"user":{"id":716427610599784400,"id_str":"716427610599784449","name":"内海啓貴","screen_name":"utsumi_akiyoshi","location":"","description":"俳優。『イムリ』俳優座劇場7月26日〜31日。『毎日が冒険～ねぇ… miss you～』紀伊國屋サザンシアター8月9日〜13日。『ナンバカ』ブルーシアター六本木9月14日〜24日。","url":"https://t.co/RIuaZ79lzX","entities":{"url":{"urls":[{"url":"https://t.co/RIuaZ79lzX","expanded_url":"http://ameblo.jp/utsumi-akiyoshi/","display_url":"ameblo.jp/utsumi-akiyosh…","indices":[0,23]}]},"description":{"urls":[]}},"protected":false,"followers_count":13182,"friends_count":126,"listed_count":762,"created_at":"Sun Apr 03 00:50:27 +0000 2016","favourites_count":462,"utc_offset":null,"time_zone":null,"geo_enabled":false,"verified":false,"statuses_count":885,"lang":"ja","contributors_enabled":false,"is_translator":false,"is_translation_enabled":false,"profile_background_color":"F5F8FA","profile_background_image_url":null,"profile_background_image_url_https":null,"profile_background_tile":false,"profile_image_url":"http://pbs.twimg.com/profile_images/886222335174254594/iJT9AqgS_normal.jpg","profile_image_url_https":"https://pbs.twimg.com/profile_images/886222335174254594/iJT9AqgS_normal.jpg","profile_link_color":"1DA1F2","profile_sidebar_border_color":"C0DEED","profile_sidebar_fill_color":"DDEEF6","profile_text_color":"333333","profile_use_background_image":true,"has_extended_profile":true,"default_profile":true,"default_profile_image":false,"following":false,"follow_request_sent":false,"notifications":false,"translator_type":"none"},"geo":null,"coordinates":null,"place":null,"contributors":null,"is_quote_status":false,"retweet_count":712,"favorite_count":836,"favorited":false,"retweeted":false,"possibly_sensitive":false,"lang":"ja"},{"created_at":"Tue Jul 18 01:01:55 +0000 2017","id":887115178608779300,"id_str":"887115178608779265","text":"ニンテンドースイッチ版『Fate/EXTELLA』の発売記念して、本日より巨神アルテラ（CV: 能登麻美子）による店内放送開始！放送時間など詳しい情報はコチラhttps://t.co/qcjY6l3EIg https://t.co/NFm2pGZViG","truncated":false,"entities":{"hashtags":[],"symbols":[],"user_mentions":[],"urls":[{"url":"https://t.co/qcjY6l3EIg","expanded_url":"http://bit.ly/2pA1DXb","display_url":"bit.ly/2pA1DXb","indices":[79,102]}],"media":[{"id":887113960645771300,"id_str":"887113960645771265","indices":[103,126],"media_url":"http://pbs.twimg.com/media/DE-pcnOUwAE3Kcv.jpg","media_url_https":"https://pbs.twimg.com/media/DE-pcnOUwAE3Kcv.jpg","url":"https://t.co/NFm2pGZViG","display_url":"pic.twitter.com/NFm2pGZViG","expanded_url":"https://twitter.com/HMV_GAME/status/887115178608779265/photo/1","type":"photo","sizes":{"small":{"w":680,"h":383,"resize":"fit"},"large":{"w":700,"h":394,"resize":"fit"},"medium":{"w":700,"h":394,"resize":"fit"},"thumb":{"w":150,"h":150,"resize":"crop"}}}]},"extended_entities":{"media":[{"id":887113960645771300,"id_str":"887113960645771265","indices":[103,126],"media_url":"http://pbs.twimg.com/media/DE-pcnOUwAE3Kcv.jpg","media_url_https":"https://pbs.twimg.com/media/DE-pcnOUwAE3Kcv.jpg","url":"https://t.co/NFm2pGZViG","display_url":"pic.twitter.com/NFm2pGZViG","expanded_url":"https://twitter.com/HMV_GAME/status/887115178608779265/photo/1","type":"photo","sizes":{"small":{"w":680,"h":383,"resize":"fit"},"large":{"w":700,"h":394,"resize":"fit"},"medium":{"w":700,"h":394,"resize":"fit"},"thumb":{"w":150,"h":150,"resize":"crop"}}}]},"metadata":{"iso_language_code":"ja","result_type":"recent"},"source":"<a href=\"http://twitter.com\" rel=\"nofollow\">Twitter Web Client</a>","in_reply_to_status_id":null,"in_reply_to_status_id_str":null,"in_reply_to_user_id":null,"in_reply_to_user_id_str":null,"in_reply_to_screen_name":null,"user":{"id":589649264,"id_str":"589649264","name":"ローチケHMVゲーム","screen_name":"HMV_GAME","location":"","description":"ゲーム時々グッズの情報をメインにHMVらしい商品から意外なものまで！ゲーム担当者による個人的なツイートや、まじめなツイートなどをチクチクお届け！","url":"http://t.co/trdHPiuoSk","entities":{"url":{"urls":[{"url":"http://t.co/trdHPiuoSk","expanded_url":"http://www.hmv.co.jp/games/","display_url":"hmv.co.jp/games/","indices":[0,22]}]},"description":{"urls":[]}},"protected":false,"followers_count":2840,"friends_count":3117,"listed_count":100,"created_at":"Fri May 25 03:26:12 +0000 2012","favourites_count":2,"utc_offset":32400,"time_zone":"Tokyo","geo_enabled":false,"verified":false,"statuses_count":5878,"lang":"ja","contributors_enabled":false,"is_translator":false,"is_translation_enabled":false,"profile_background_color":"DBE9ED","profile_background_image_url":"http://abs.twimg.com/images/themes/theme17/bg.gif","profile_background_image_url_https":"https://abs.twimg.com/images/themes/theme17/bg.gif","profile_background_tile":false,"profile_image_url":"http://pbs.twimg.com/profile_images/669249319841624064/n7ysLffr_normal.png","profile_image_url_https":"https://pbs.twimg.com/profile_images/669249319841624064/n7ysLffr_normal.png","profile_link_color":"CC3366","profile_sidebar_border_color":"DBE9ED","profile_sidebar_fill_color":"E6F6F9","profile_text_color":"333333","profile_use_background_image":true,"has_extended_profile":false,"default_profile":false,"default_profile_image":false,"following":false,"follow_request_sent":false,"notifications":false,"translator_type":"none"},"geo":null,"coordinates":null,"place":null,"contributors":null,"is_quote_status":false,"retweet_count":593,"favorite_count":367,"favorited":false,"retweeted":false,"possibly_sensitive":false,"lang":"ja"},{"created_at":"Tue Jul 18 01:01:02 +0000 2017","id":887114958068109300,"id_str":"887114958068109312","text":"＼100名様に「#ドデカミン」1ケースが当たる／\nさらに当選者の中から12名様には「#ドデカマスク 名句入りオリジナルTシャツ」もプレゼント！アカウントをフォロー＆この投稿をRTで応募完了！\n#ドデカマスクTシャツプレゼント… https://t.co/PwqX1MtkWb","truncated":true,"entities":{"hashtags":[{"text":"ドデカミン","indices":[8,14]},{"text":"ドデカマスク","indices":[42,49]},{"text":"ドデカマスクTシャツプレゼント","indices":[96,112]}],"symbols":[],"user_mentions":[],"urls":[{"url":"https://t.co/PwqX1MtkWb","expanded_url":"https://twitter.com/i/web/status/887114958068109312","display_url":"twitter.com/i/web/status/8…","indices":[114,137]}]},"metadata":{"iso_language_code":"ja","result_type":"recent"},"source":"<a href=\"https://ads.twitter.com\" rel=\"nofollow\">Twitter Ads</a>","in_reply_to_status_id":null,"in_reply_to_status_id_str":null,"in_reply_to_user_id":null,"in_reply_to_user_id_str":null,"in_reply_to_screen_name":null,"user":{"id":717628618906570800,"id_str":"717628618906570752","name":"アサヒ飲料AsahiSoftDrinks","screen_name":"asahiinryo_jp","location":"","description":"アサヒ飲料公式アカウントです！商品やキャンペーン情報、商品にまつわる楽しくお得な情報を紹介します。原則DM・リプライやフォロー返しは行っておりません。ご了承ください。 【ご利用規約】https://t.co/EyBGeDgr2z 【お問い合わせ】https://t.co/eoPQRl1fBF","url":"https://t.co/de3P5zrwdX","entities":{"url":{"urls":[{"url":"https://t.co/de3P5zrwdX","expanded_url":"http://www.asahiinryo.co.jp/","display_url":"asahiinryo.co.jp","indices":[0,23]}]},"description":{"urls":[{"url":"https://t.co/EyBGeDgr2z","expanded_url":"http://bit.ly/1TcbUC5","display_url":"bit.ly/1TcbUC5","indices":[91,114]},{"url":"https://t.co/eoPQRl1fBF","expanded_url":"http://bit.ly/1NrbSag","display_url":"bit.ly/1NrbSag","indices":[123,146]}]}},"protected":false,"followers_count":218405,"friends_count":17,"listed_count":396,"created_at":"Wed Apr 06 08:22:50 +0000 2016","favourites_count":0,"utc_offset":32400,"time_zone":"Tokyo","geo_enabled":true,"verified":true,"statuses_count":348922,"lang":"ja","contributors_enabled":false,"is_translator":false,"is_translation_enabled":false,"profile_background_color":"F5F8FA","profile_background_image_url":null,"profile_background_image_url_https":null,"profile_background_tile":false,"profile_image_url":"http://pbs.twimg.com/profile_images/876601951705681920/T_23nnwz_normal.jpg","profile_image_url_https":"https://pbs.twimg.com/profile_images/876601951705681920/T_23nnwz_normal.jpg","profile_banner_url":"https://pbs.twimg.com/profile_banners/717628618906570752/1498783575","profile_link_color":"1DA1F2","profile_sidebar_border_color":"C0DEED","profile_sidebar_fill_color":"DDEEF6","profile_text_color":"333333","profile_use_background_image":true,"has_extended_profile":false,"default_profile":true,"default_profile_image":false,"following":false,"follow_request_sent":false,"notifications":false,"translator_type":"none"},"geo":null,"coordinates":null,"place":null,"contributors":null,"is_quote_status":false,"retweet_count":2653,"favorite_count":343,"favorited":false,"retweeted":false,"possibly_sensitive":false,"lang":"ja"},{"created_at":"Tue Jul 18 01:00:23 +0000 2017","id":887114796113444900,"id_str":"887114796113444864","text":"舞台「黒執事」全キャスト発表！植原卓也＆佐々木喜英が2年ぶり復帰 https://t.co/tdhwEQmkKp https://t.co/2LsmYWaEmw","truncated":false,"entities":{"hashtags":[],"symbols":[],"user_mentions":[],"urls":[{"url":"https://t.co/tdhwEQmkKp","expanded_url":"http://natalie.mu/comic/news/241123","display_url":"natalie.mu/comic/news/241…","indices":[33,56]}],"media":[{"id":887114777876545500,"id_str":"887114777876545538","indices":[57,80],"media_url":"http://pbs.twimg.com/media/DE-qMLpUwAIzWj-.jpg","media_url_https":"https://pbs.twimg.com/media/DE-qMLpUwAIzWj-.jpg","url":"https://t.co/2LsmYWaEmw","display_url":"pic.twitter.com/2LsmYWaEmw","expanded_url":"https://twitter.com/comic_natalie/status/887114796113444864/photo/1","type":"photo","sizes":{"thumb":{"w":150,"h":150,"resize":"crop"},"medium":{"w":640,"h":303,"resize":"fit"},"large":{"w":640,"h":303,"resize":"fit"},"small":{"w":640,"h":303,"resize":"fit"}}}]},"extended_entities":{"media":[{"id":887114777876545500,"id_str":"887114777876545538","indices":[57,80],"media_url":"http://pbs.twimg.com/media/DE-qMLpUwAIzWj-.jpg","media_url_https":"https://pbs.twimg.com/media/DE-qMLpUwAIzWj-.jpg","url":"https://t.co/2LsmYWaEmw","display_url":"pic.twitter.com/2LsmYWaEmw","expanded_url":"https://twitter.com/comic_natalie/status/887114796113444864/photo/1","type":"photo","sizes":{"thumb":{"w":150,"h":150,"resize":"crop"},"medium":{"w":640,"h":303,"resize":"fit"},"large":{"w":640,"h":303,"resize":"fit"},"small":{"w":640,"h":303,"resize":"fit"}}},{"id":887114784499318800,"id_str":"887114784499318784","indices":[57,80],"media_url":"http://pbs.twimg.com/media/DE-qMkUUQAAL7-7.jpg","media_url_https":"https://pbs.twimg.com/media/DE-qMkUUQAAL7-7.jpg","url":"https://t.co/2LsmYWaEmw","display_url":"pic.twitter.com/2LsmYWaEmw","expanded_url":"https://twitter.com/comic_natalie/status/887114796113444864/photo/1","type":"photo","sizes":{"medium":{"w":640,"h":853,"resize":"fit"},"large":{"w":640,"h":853,"resize":"fit"},"thumb":{"w":150,"h":150,"resize":"crop"},"small":{"w":510,"h":680,"resize":"fit"}}},{"id":887114789247266800,"id_str":"887114789247266816","indices":[57,80],"media_url":"http://pbs.twimg.com/media/DE-qM2AUMAAKYVi.jpg","media_url_https":"https://pbs.twimg.com/media/DE-qM2AUMAAKYVi.jpg","url":"https://t.co/2LsmYWaEmw","display_url":"pic.twitter.com/2LsmYWaEmw","expanded_url":"https://twitter.com/comic_natalie/status/887114796113444864/photo/1","type":"photo","sizes":{"medium":{"w":640,"h":853,"resize":"fit"},"thumb":{"w":150,"h":150,"resize":"crop"},"large":{"w":640,"h":853,"resize":"fit"},"small":{"w":510,"h":680,"resize":"fit"}}},{"id":887114793638699000,"id_str":"887114793638699008","indices":[57,80],"media_url":"http://pbs.twimg.com/media/DE-qNGXUIAAdXqc.jpg","media_url_https":"https://pbs.twimg.com/media/DE-qNGXUIAAdXqc.jpg","url":"https://t.co/2LsmYWaEmw","display_url":"pic.twitter.com/2LsmYWaEmw","expanded_url":"https://twitter.com/comic_natalie/status/887114796113444864/photo/1","type":"photo","sizes":{"medium":{"w":640,"h":853,"resize":"fit"},"large":{"w":640,"h":853,"resize":"fit"},"thumb":{"w":150,"h":150,"resize":"crop"},"small":{"w":510,"h":680,"resize":"fit"}}}]},"metadata":{"iso_language_code":"ja","result_type":"recent"},"source":"<a href=\"http://natalie.mu/comic\" rel=\"nofollow\">comic_natalie</a>","in_reply_to_status_id":null,"in_reply_to_status_id_str":null,"in_reply_to_user_id":null,"in_reply_to_user_id_str":null,"in_reply_to_screen_name":null,"user":{"id":18622184,"id_str":"18622184","name":"コミックナタリー","screen_name":"comic_natalie","location":"東京","description":"マンガのニュースを毎日発信するコミックナタリーの記事ヘッドラインをお届け。音楽ナタリー（@natalie_mu）、お笑いナタリー（@owarai_natalie）、映画ナタリー（@eiga_natalie）、ステージナタリー（@stage_natalie）ナタリーストア（@natalie_store）も併せてどうぞ。","url":"http://t.co/oDRqtG4rhU","entities":{"url":{"urls":[{"url":"http://t.co/oDRqtG4rhU","expanded_url":"http://natalie.mu/comic","display_url":"natalie.mu/comic","indices":[0,22]}]},"description":{"urls":[]}},"protected":false,"followers_count":318391,"friends_count":6,"listed_count":9750,"created_at":"Mon Jan 05 03:33:30 +0000 2009","favourites_count":57,"utc_offset":32400,"time_zone":"Tokyo","geo_enabled":false,"verified":true,"statuses_count":54328,"lang":"ja","contributors_enabled":false,"is_translator":false,"is_translation_enabled":false,"profile_background_color":"E4E0D9","profile_background_image_url":"http://pbs.twimg.com/profile_background_images/4244500/comic_bg.png","profile_background_image_url_https":"https://pbs.twimg.com/profile_background_images/4244500/comic_bg.png","profile_background_tile":false,"profile_image_url":"http://pbs.twimg.com/profile_images/541890424114126848/EEFqjOib_normal.png","profile_image_url_https":"https://pbs.twimg.com/profile_images/541890424114126848/EEFqjOib_normal.png","profile_banner_url":"https://pbs.twimg.com/profile_banners/18622184/1418031708","profile_link_color":"7DB739","profile_sidebar_border_color":"E4E0D9","profile_sidebar_fill_color":"FFFFFF","profile_text_color":"333333","profile_use_background_image":true,"has_extended_profile":false,"default_profile":false,"default_profile_image":false,"following":false,"follow_request_sent":false,"notifications":false,"translator_type":"none"},"geo":null,"coordinates":null,"place":null,"contributors":null,"is_quote_status":false,"retweet_count":1574,"favorite_count":1375,"favorited":false,"retweeted":false,"possibly_sensitive":false,"lang":"ja"},{"created_at":"Tue Jul 18 01:00:22 +0000 2017","id":887114791830945800,"id_str":"887114791830945792","text":"「スプラトゥーン2」発売まで、あと3日。\nそうそう、ガチで戦うエクストリームバトル「ガチマッチ」も忘れてはいけない。\n友達とチームを組んで「リーグマッチ」で高みを目指すのも良いだろう。\nそして、謎のバイト「サーモンラン」。\nクマサ… https://t.co/OX3TA3JJAw","truncated":true,"entities":{"hashtags":[],"symbols":[],"user_mentions":[],"urls":[{"url":"https://t.co/OX3TA3JJAw","expanded_url":"https://twitter.com/i/web/status/887114791830945792","display_url":"twitter.com/i/web/status/8…","indices":[117,140]}]},"metadata":{"iso_language_code":"ja","result_type":"recent"},"source":"<a href=\"http://twitter.com\" rel=\"nofollow\">Twitter Web Client</a>","in_reply_to_status_id":null,"in_reply_to_status_id_str":null,"in_reply_to_user_id":null,"in_reply_to_user_id_str":null,"in_reply_to_screen_name":null,"user":{"id":2888006497,"id_str":"2888006497","name":"Splatoon（スプラトゥーン）","screen_name":"SplatoonJP","location":"","description":"『スプラトゥーン』公式総合アカウント。イカ研究所の調査報告（ゲーム情報）やお知らせをお伝えします。最新作の『スプラトゥーン2』は2017年7月21日（金）発売予定。ご質問・お問い合わせにはお答えしておりませんのでご容赦ください。 ※イカ研究所は実在の人物、団体とは一切関係ございません。","url":"https://t.co/yCMNfZlVpz","entities":{"url":{"urls":[{"url":"https://t.co/yCMNfZlVpz","expanded_url":"https://www.nintendo.co.jp/switch/aab6a/index.html","display_url":"nintendo.co.jp/switch/aab6a/i…","indices":[0,23]}]},"description":{"urls":[]}},"protected":false,"followers_count":660940,"friends_count":1,"listed_count":6461,"created_at":"Mon Nov 03 01:36:06 +0000 2014","favourites_count":0,"utc_offset":32400,"time_zone":"Tokyo","geo_enabled":false,"verified":true,"statuses_count":1470,"lang":"ja","contributors_enabled":false,"is_translator":false,"is_translation_enabled":false,"profile_background_color":"000000","profile_background_image_url":"http://pbs.twimg.com/profile_background_images/530105343452274688/WJl6dNx5.jpeg","profile_background_image_url_https":"https://pbs.twimg.com/profile_background_images/530105343452274688/WJl6dNx5.jpeg","profile_background_tile":false,"profile_image_url":"http://pbs.twimg.com/profile_images/819765217957552132/1WftJJM1_normal.jpg","profile_image_url_https":"https://pbs.twimg.com/profile_images/819765217957552132/1WftJJM1_normal.jpg","profile_banner_url":"https://pbs.twimg.com/profile_banners/2888006497/1484282224","profile_link_color":"000000","profile_sidebar_border_color":"000000","profile_sidebar_fill_color":"E3E2DE","profile_text_color":"634047","profile_use_background_image":true,"has_extended_profile":false,"default_profile":false,"default_profile_image":false,"following":false,"follow_request_sent":false,"notifications":false,"translator_type":"none"},"geo":null,"coordinates":null,"place":null,"contributors":null,"is_quote_status":false,"retweet_count":2986,"favorite_count":5600,"favorited":false,"retweeted":false,"possibly_sensitive":false,"lang":"ja"},{"created_at":"Tue Jul 18 01:00:12 +0000 2017","id":887114747002241000,"id_str":"887114747002241024","text":"ミュージカル「黒執事」追加キャストに植原卓也、佐々木喜英、和泉宗兵 https://t.co/l1Q235mwvf #古川雄大 #内川蓮生 #味方良介 #原嶋元久 #髙木俊 #寺山武志 #内海啓貴 #河合龍之介 https://t.co/x3xIP5Q4Mi","truncated":false,"entities":{"hashtags":[{"text":"古川雄大","indices":[58,63]},{"text":"内川蓮生","indices":[64,69]},{"text":"味方良介","indices":[70,75]},{"text":"原嶋元久","indices":[76,81]},{"text":"髙木俊","indices":[82,86]},{"text":"寺山武志","indices":[87,92]},{"text":"内海啓貴","indices":[93,98]},{"text":"河合龍之介","indices":[99,105]}],"symbols":[],"user_mentions":[],"urls":[{"url":"https://t.co/l1Q235mwvf","expanded_url":"http://natalie.mu/stage/news/241129","display_url":"natalie.mu/stage/news/241…","indices":[34,57]}],"media":[{"id":887114730338271200,"id_str":"887114730338271233","indices":[106,129],"media_url":"http://pbs.twimg.com/media/DE-qJajUQAE6ymp.jpg","media_url_https":"https://pbs.twimg.com/media/DE-qJajUQAE6ymp.jpg","url":"https://t.co/x3xIP5Q4Mi","display_url":"pic.twitter.com/x3xIP5Q4Mi","expanded_url":"https://twitter.com/stage_natalie/status/887114747002241024/photo/1","type":"photo","sizes":{"thumb":{"w":150,"h":150,"resize":"crop"},"medium":{"w":640,"h":303,"resize":"fit"},"large":{"w":640,"h":303,"resize":"fit"},"small":{"w":640,"h":303,"resize":"fit"}}}]},"extended_entities":{"media":[{"id":887114730338271200,"id_str":"887114730338271233","indices":[106,129],"media_url":"http://pbs.twimg.com/media/DE-qJajUQAE6ymp.jpg","media_url_https":"https://pbs.twimg.com/media/DE-qJajUQAE6ymp.jpg","url":"https://t.co/x3xIP5Q4Mi","display_url":"pic.twitter.com/x3xIP5Q4Mi","expanded_url":"https://twitter.com/stage_natalie/status/887114747002241024/photo/1","type":"photo","sizes":{"thumb":{"w":150,"h":150,"resize":"crop"},"medium":{"w":640,"h":303,"resize":"fit"},"large":{"w":640,"h":303,"resize":"fit"},"small":{"w":640,"h":303,"resize":"fit"}}},{"id":887114734993981400,"id_str":"887114734993981440","indices":[106,129],"media_url":"http://pbs.twimg.com/media/DE-qJr5UwAAgt9t.jpg","media_url_https":"https://pbs.twimg.com/media/DE-qJr5UwAAgt9t.jpg","url":"https://t.co/x3xIP5Q4Mi","display_url":"pic.twitter.com/x3xIP5Q4Mi","expanded_url":"https://twitter.com/stage_natalie/status/887114747002241024/photo/1","type":"photo","sizes":{"thumb":{"w":150,"h":150,"resize":"crop"},"large":{"w":640,"h":853,"resize":"fit"},"medium":{"w":640,"h":853,"resize":"fit"},"small":{"w":510,"h":680,"resize":"fit"}}},{"id":887114739922292700,"id_str":"887114739922292736","indices":[106,129],"media_url":"http://pbs.twimg.com/media/DE-qJ-QU0AAYtoF.jpg","media_url_https":"https://pbs.twimg.com/media/DE-qJ-QU0AAYtoF.jpg","url":"https://t.co/x3xIP5Q4Mi","display_url":"pic.twitter.com/x3xIP5Q4Mi","expanded_url":"https://twitter.com/stage_natalie/status/887114747002241024/photo/1","type":"photo","sizes":{"medium":{"w":640,"h":853,"resize":"fit"},"thumb":{"w":150,"h":150,"resize":"crop"},"large":{"w":640,"h":853,"resize":"fit"},"small":{"w":510,"h":680,"resize":"fit"}}},{"id":887114744112402400,"id_str":"887114744112402433","indices":[106,129],"media_url":"http://pbs.twimg.com/media/DE-qKN3U0AEoQc8.jpg","media_url_https":"https://pbs.twimg.com/media/DE-qKN3U0AEoQc8.jpg","url":"https://t.co/x3xIP5Q4Mi","display_url":"pic.twitter.com/x3xIP5Q4Mi","expanded_url":"https://twitter.com/stage_natalie/status/887114747002241024/photo/1","type":"photo","sizes":{"medium":{"w":640,"h":853,"resize":"fit"},"large":{"w":640,"h":853,"resize":"fit"},"thumb":{"w":150,"h":150,"resize":"crop"},"small":{"w":510,"h":680,"resize":"fit"}}}]},"metadata":{"iso_language_code":"ja","result_type":"recent"},"source":"<a href=\"http://natalie.mu/stage\" rel=\"nofollow\">ステージナタリー</a>","in_reply_to_status_id":null,"in_reply_to_status_id_str":null,"in_reply_to_user_id":null,"in_reply_to_user_id_str":null,"in_reply_to_screen_name":null,"user":{"id":4416480253,"id_str":"4416480253","name":"ステージナタリー","screen_name":"stage_natalie","location":"東京","description":"舞台・演劇の最新ニュースを毎日発信する「ステージナタリー」の記事ヘッドラインをお届け。音楽ナタリー（@natalie_mu）、コミックナタリー（@comic_natalie）、お笑いナタリー（@owarai_natalie）、映画ナタリー（@eiga_natalie）、ナタリーストア（@natalie_store）も。","url":"https://t.co/uvOaz4qqEN","entities":{"url":{"urls":[{"url":"https://t.co/uvOaz4qqEN","expanded_url":"http://natalie.mu/stage","display_url":"natalie.mu/stage","indices":[0,23]}]},"description":{"urls":[]}},"protected":false,"followers_count":38297,"friends_count":5,"listed_count":891,"created_at":"Tue Dec 01 03:37:48 +0000 2015","favourites_count":0,"utc_offset":null,"time_zone":null,"geo_enabled":false,"verified":false,"statuses_count":6283,"lang":"ja","contributors_enabled":false,"is_translator":false,"is_translation_enabled":false,"profile_background_color":"000000","profile_background_image_url":"http://abs.twimg.com/images/themes/theme1/bg.png","profile_background_image_url_https":"https://abs.twimg.com/images/themes/theme1/bg.png","profile_background_tile":false,"profile_image_url":"http://pbs.twimg.com/profile_images/694343467862880256/b4jdvFhq_normal.png","profile_image_url_https":"https://pbs.twimg.com/profile_images/694343467862880256/b4jdvFhq_normal.png","profile_banner_url":"https://pbs.twimg.com/profile_banners/4416480253/1454379379","profile_link_color":"BEA968","profile_sidebar_border_color":"000000","profile_sidebar_fill_color":"000000","profile_text_color":"000000","profile_use_background_image":false,"has_extended_profile":false,"default_profile":false,"default_profile_image":false,"following":false,"follow_request_sent":false,"notifications":false,"translator_type":"none"},"geo":null,"coordinates":null,"place":null,"contributors":null,"is_quote_status":false,"retweet_count":1642,"favorite_count":1210,"favorited":false,"retweeted":false,"possibly_sensitive":false,"lang":"ja"},{"created_at":"Tue Jul 18 01:00:07 +0000 2017","id":887114726408192000,"id_str":"887114726408192000","text":"『ミュージカル「黒執事」-Tango on the Campania-』お待たせいたしました！本日遂に待望の全キャスト発表。復活そして続投、また新キャストも集結！豪華絢爛なオールキャストビジュアルも大解禁！詳細は公式HPへ！\n→n… https://t.co/mQw8F2F6lB","truncated":true,"entities":{"hashtags":[],"symbols":[],"user_mentions":[],"urls":[{"url":"https://t.co/mQw8F2F6lB","expanded_url":"https://twitter.com/i/web/status/887114726408192000","display_url":"twitter.com/i/web/status/8…","indices":[117,140]}]},"metadata":{"iso_language_code":"ja","result_type":"recent"},"source":"<a href=\"http://twitter.com/download/iphone\" rel=\"nofollow\">Twitter for iPhone</a>","in_reply_to_status_id":null,"in_reply_to_status_id_str":null,"in_reply_to_user_id":null,"in_reply_to_user_id_str":null,"in_reply_to_screen_name":null,"user":{"id":2583812948,"id_str":"2583812948","name":"ミュージカル「黒執事」公式アカウント","screen_name":"namashitsujijp","location":"2014 ","description":"ミュージカル「黒執事」公式ツイッターアカウントです。ツイッターへのご質問はすぐにお答えできないこともございます。各種お問い合わせ先はhttps://t.co/jrjFHeASnV をご参照ください。（c)2017 枢やな／ミュージカル黒執事プロジェクト","url":"https://t.co/omH3oZlYSx","entities":{"url":{"urls":[{"url":"https://t.co/omH3oZlYSx","expanded_url":"http://www.namashitsuji.jp","display_url":"namashitsuji.jp","indices":[0,23]}]},"description":{"urls":[{"url":"https://t.co/jrjFHeASnV","expanded_url":"http://namashitsuji.jp/","display_url":"namashitsuji.jp","indices":[66,89]}]}},"protected":false,"followers_count":48066,"friends_count":69,"listed_count":752,"created_at":"Mon Jun 23 11:02:15 +0000 2014","favourites_count":10,"utc_offset":28800,"time_zone":"Irkutsk","geo_enabled":false,"verified":false,"statuses_count":2040,"lang":"ja","contributors_enabled":false,"is_translator":false,"is_translation_enabled":false,"profile_background_color":"000000","profile_background_image_url":"http://abs.twimg.com/images/themes/theme1/bg.png","profile_background_image_url_https":"https://abs.twimg.com/images/themes/theme1/bg.png","profile_background_tile":false,"profile_image_url":"http://pbs.twimg.com/profile_images/868277076998017024/1K3yj3Cv_normal.jpg","profile_image_url_https":"https://pbs.twimg.com/profile_images/868277076998017024/1K3yj3Cv_normal.jpg","profile_banner_url":"https://pbs.twimg.com/profile_banners/2583812948/1460953305","profile_link_color":"DD2E44","profile_sidebar_border_color":"000000","profile_sidebar_fill_color":"000000","profile_text_color":"000000","profile_use_background_image":false,"has_extended_profile":false,"default_profile":false,"default_profile_image":false,"following":false,"follow_request_sent":false,"notifications":false,"translator_type":"none"},"geo":null,"coordinates":null,"place":null,"contributors":null,"is_quote_status":false,"retweet_count":3293,"favorite_count":2713,"favorited":false,"retweeted":false,"possibly_sensitive":false,"lang":"ja"},{"created_at":"Tue Jul 18 01:00:02 +0000 2017","id":887114705743093800,"id_str":"887114705743093760","text":"＼#新マウントレーニアが当たる🆕／\nマカダミアナッツモカ☕️\n1ケースを10名様にプレゼント🎁\n\n▼応募は7/24 23:59まで！\n①@morinaga_milk_ をフォロー\n②この投稿をリツイート\n\n詳細はこちら▼\nhttps://t.co/QbqQgpxZUK","truncated":false,"entities":{"hashtags":[{"text":"新マウントレーニアが当たる","indices":[1,15]}],"symbols":[],"user_mentions":[{"screen_name":"morinaga_milk_","name":"森永乳業＠もーりー","id":734977026679930900,"id_str":"734977026679930880","indices":[68,83]}],"urls":[{"url":"https://t.co/QbqQgpxZUK","expanded_url":"https://cards.twitter.com/cards/18ce54d2if6/4ikoz","display_url":"cards.twitter.com/cards/18ce54d2…","indices":[111,134]}]},"metadata":{"iso_language_code":"ja","result_type":"recent"},"source":"<a href=\"https://about.twitter.com/products/tweetdeck\" rel=\"nofollow\">TweetDeck</a>","in_reply_to_status_id":null,"in_reply_to_status_id_str":null,"in_reply_to_user_id":null,"in_reply_to_user_id_str":null,"in_reply_to_screen_name":null,"user":{"id":734977026679930900,"id_str":"734977026679930880","name":"森永乳業＠もーりー","screen_name":"morinaga_milk_","location":"","description":"森永乳業の公式アカウントです。「Newの森」（ https://t.co/86VZ2caxk8 ）からやって来た森の妖精「もーりー」が、商品やイベントなど、色々な情報をお届けします♪（平日：9:00～17:30）※DMは受け付けておりません。お問合せはお客さま相談室（TEL：0120-369-744）まで。","url":"https://t.co/yX55U3AdV1","entities":{"url":{"urls":[{"url":"https://t.co/yX55U3AdV1","expanded_url":"http://www.morinagamilk.co.jp/","display_url":"morinagamilk.co.jp","indices":[0,23]}]},"description":{"urls":[{"url":"https://t.co/86VZ2caxk8","expanded_url":"http://newnomori.jp/","display_url":"newnomori.jp","indices":[24,47]}]}},"protected":false,"followers_count":55033,"friends_count":1494,"listed_count":131,"created_at":"Tue May 24 05:19:13 +0000 2016","favourites_count":10270,"utc_offset":32400,"time_zone":"Tokyo","geo_enabled":true,"verified":true,"statuses_count":64180,"lang":"ja","contributors_enabled":false,"is_translator":false,"is_translation_enabled":false,"profile_background_color":"000000","profile_background_image_url":"http://abs.twimg.com/images/themes/theme1/bg.png","profile_background_image_url_https":"https://abs.twimg.com/images/themes/theme1/bg.png","profile_background_tile":false,"profile_image_url":"http://pbs.twimg.com/profile_images/878150112886669313/dEeWB4Qq_normal.jpg","profile_image_url_https":"https://pbs.twimg.com/profile_images/878150112886669313/dEeWB4Qq_normal.jpg","profile_banner_url":"https://pbs.twimg.com/profile_banners/734977026679930880/1491797429","profile_link_color":"E70012","profile_sidebar_border_color":"000000","profile_sidebar_fill_color":"000000","profile_text_color":"000000","profile_use_background_image":false,"has_extended_profile":true,"default_profile":false,"default_profile_image":false,"following":false,"follow_request_sent":false,"notifications":false,"translator_type":"none"},"geo":null,"coordinates":null,"place":null,"contributors":null,"is_quote_status":false,"retweet_count":1710,"favorite_count":203,"favorited":false,"retweeted":false,"possibly_sensitive":false,"lang":"ja"}],"search_metadata":{"completed_in":0.194,"max_id":887122163118911500,"max_id_str":"887122163118911488","next_results":"?max_id=887114705743093759&q=lang%3Aja%20min_retweets%3A500&include_entities=1","query":"lang%3Aja+min_retweets%3A500","refresh_url":"?since_id=887122163118911488&q=lang%3Aja%20min_retweets%3A500&include_entities=1","count":15,"since_id":0,"since_id_str":"0"}}